Workbook

Sheet Per Card Cost
A1: Card Name | B1: Purchase Price | C1: Packaging Type | D1: Penny Sleeve | E1: Top Loader | F1: Hobby Armor | G1: Team Bag | H1: Bubble Mailer | I1: Ding Defend Envelope | J1: Shipping Label | K1: TOTAL COST | L1: Sale Price | M1: Buyer Shipping Paid | N1: Sales Tax Collected | O1: Order Total (Buyer Paid) | P1: eBay Transaction Fees (Actual) | Q1: eBay Fees (Estimate) | R1: Insertion Fee | S1: Order Earnings (Payout) | T1: Net Profit (After COGS+Materials) | U1: Break Even Item Price (Estimate) | V1: NET PROFIT (Old - Deprecated) | W1: BREAK EVEN (Old - Deprecated) | X1: Profit Margin % (Net/Revenue) | Y1: ROI % (Net/Total Cost) | Z1: Fee % of Order (Est) | AA1: Net Margin % (Net/Sale Price) | AB1: Notes | AC1: Date Listed | AD1: Date Sold | AE1: Days to Sell
A2: Joe Burrow 2025 Panini Score Patch MEM Stars of NFL Bengals Insert #SNJ-JBW | B2: 0.35 | C2: ESE (Ding Defend) | D2: =IF($A2="","",1*'Material Costs'!$D$3) -> 0.01716 | E2: =IF($A2="","",1*'Material Costs'!$D$2) -> 0.1699 | F2: 0 | G2: =IF($A2="","",1*'Material Costs'!$D$7) -> 0.0525 | H2: =IF($A2="","",IF($C2="Bubble Mailer",1,0)*'Material Costs'!$D$5) -> 0 | I2: =IF($A2="","",IF($C2="ESE (Ding Defend)",1,0)*'Material Costs'!$D$4) -> 0.227 | J2: 1.03 | K2: =IF($A2="","",SUM($B2:$J2)) -> 1.84656 | L2: 3.05 | M2: 1.49 | N2: 0.47 | O2: =IF($A2="","",SUM($L2:$N2)) -> 5.01 | P2: 0.96 | Q2: 0 | R2: 0 | S2: =IF($A2="","",IF($O2="", "", ROUND($O2 - IF($P2<>"",$P2,$Q2) - $R2,2))) -> 4.05 | T2: =IF($A2="","",IF($S2="", "", ROUND($S2 - $K2,2))) -> 2.2 | U2: =IF($A2="","",IF($K2="", "", ROUND((($K2 + Settings!$B$3 + $R2) - IF($M2="",0,$M2))/(1-Settings!$B$2),2))) -> 0.76 | V2: =IF($A2="","",$L2-($L2*Settings!$B$2)-$J2-($B2+SUM($D2:$I2))) -> 0.799315 | W2: =IF($A2="","",(($B2+SUM($D2:$I2)+$J2+Settings!$B$3)/(1-Settings!$B$2))-$M2) -> 0.98442075 | X2: =IF($A2="","",IF($O2="", "", IFERROR($T2/$O2, ""))) -> 0.43912176 | Y2: =IF($A2="","",IF($K2="", "", IFERROR($T2/$K2, ""))) -> 1.1914046 | Z2: =IF($A2="","",IF($O2="", "", IFERROR($Q2/$O2, ""))) -> 0 | AA2: =IF($A2="","",IF($L2="", "", IFERROR($T2/$L2, ""))) -> 0.72131148 | AE2: =IF($A2="","",IF(OR($AC2="", $AD2=""),"", $AD2-$AC2))
A3: Terrance Ferguson 2025 Panini Rookies & Stars Crusade Red Plaid Prizm #27 RC | B3: 0.35 | C3: ESE (Ding Defend) | D3: =IF($A3="","",1*'Material Costs'!$D$3) -> 0.01716 | E3: =IF($A3="","",1*'Material Costs'!$D$2) -> 0.1699 | F3: =IF($A3="","",IF($C3="Bubble Mailer",2,1)*'Material Costs'!$D$6) -> 0.1712 | G3: =IF($A3="","",1*'Material Costs'!$D$7) -> 0.0525 | H3: =IF($A3="","",IF($C3="Bubble Mailer",1,0)*'Material Costs'!$D$5) -> 0 | I3: =IF($A3="","",IF($C3="ESE (Ding Defend)",1,0)*'Material Costs'!$D$4) -> 0.227 | J3: 1.03 | K3: =IF($A3="","",SUM($B3:$J3)) -> 2.01776 | L3: 2.25 | M3: 1.49 | N3: 0 | O3: =IF($A3="","",SUM($L3:$N3)) -> 3.74 | Q3: =IF($A3="","",IF($O3="", "", ROUND($O3*Settings!$B$2+Settings!$B$3,2))) -> 0.8 | R3: 0 | S3: =IF($A3="","",IF($O3="", "", ROUND($O3 - IF($P3<>"",$P3,$Q3) - $R3,2))) -> 2.94 | T3: =IF($A3="","",IF($S3="", "", ROUND($S3 - $K3,2))) -> 0.92 | U3: =IF($A3="","",IF($K3="", "", ROUND((($K3 + Settings!$B$3 + $R3) - IF($M3="",0,$M3))/(1-Settings!$B$2),2))) -> 0.95 | V3: =IF($A3="","",$L3-($L3*Settings!$B$2)-$J3-($B3+SUM($D3:$I3))) -> -0.065885 | W3: =IF($A3="","",(($B3+SUM($D3:$I3)+$J3+Settings!$B$3)/(1-Settings!$B$2))-$M3) -> 1.1817695 | X3: =IF($A3="","",IF($O3="", "", IFERROR($T3/$O3, ""))) -> 0.2459893 | Y3: =IF($A3="","",IF($K3="", "", IFERROR($T3/$K3, ""))) -> 0.45595115 | Z3: =IF($A3="","",IF($O3="", "", IFERROR($Q3/$O3, ""))) -> 0.21390374 | AA3: =IF($A3="","",IF($L3="", "", IFERROR($T3/$L3, ""))) -> 0.40888889 | AE3: =IF($A3="","",IF(OR($AC3="", $AD3=""),"", $AD3-$AC3))
A4: Drake Maye 2024 Donruss Optic Rated Rookie Green Hyper Prizm #229 RC Patriots | B4: 0.55 | C4: Bubble Mailer | D4: =IF($A4="","",1*'Material Costs'!$D$3) -> 0.01716 | E4: =IF($A4="","",1*'Material Costs'!$D$2) -> 0.1699 | F4: =IF($A4="","",IF($C4="Bubble Mailer",2,1)*'Material Costs'!$D$6) -> 0.3424 | G4: =IF($A4="","",1*'Material Costs'!$D$7) -> 0.0525 | H4: =IF($A4="","",IF($C4="Bubble Mailer",1,0)*'Material Costs'!$D$5) -> 0.1976 | I4: =IF($A4="","",IF($C4="ESE (Ding Defend)",1,0)*'Material Costs'!$D$4) -> 0 | J4: 4.78 | K4: =IF($A4="","",SUM($B4:$J4)) -> 6.10956 | L4: 42 | M4: 4.78 | N4: 0 | O4: =IF($A4="","",SUM($L4:$N4)) -> 46.78 | Q4: =IF($A4="","",IF($O4="", "", ROUND($O4*Settings!$B$2+Settings!$B$3,2))) -> 6.5 | R4: 0 | S4: =IF($A4="","",IF($O4="", "", ROUND($O4 - IF($P4<>"",$P4,$Q4) - $R4,2))) -> 40.28 | T4: =IF($A4="","",IF($S4="", "", ROUND($S4 - $K4,2))) -> 34.17 | U4: =IF($A4="","",IF($K4="", "", ROUND((($K4 + Settings!$B$3 + $R4) - IF($M4="",0,$M4))/(1-Settings!$B$2),2))) -> 1.88 | V4: =IF($A4="","",$L4-($L4*Settings!$B$2)-$J4-($B4+SUM($D4:$I4))) -> 30.32544 | W4: =IF($A4="","",(($B4+SUM($D4:$I4)+$J4+Settings!$B$3)/(1-Settings!$B$2))-$M4) -> 2.6085418 | X4: =IF($A4="","",IF($O4="", "", IFERROR($T4/$O4, ""))) -> 0.73044036 | Y4: =IF($A4="","",IF($K4="", "", IFERROR($T4/$K4, ""))) -> 5.5928741 | Z4: =IF($A4="","",IF($O4="", "", IFERROR($Q4/$O4, ""))) -> 0.13894827 | AA4: =IF($A4="","",IF($L4="", "", IFERROR($T4/$L4, ""))) -> 0.81357143 | AE4: =IF($A4="","",IF(OR($AC4="", $AD4=""),"", $AD4-$AC4))
A5: Caleb Williams Rookie RC 2024 Panini Draft Class DC-CWS Chicago Bears | B5: 0.35 | C5: ESE (Ding Defend) | D5: =IF($A5="","",1*'Material Costs'!$D$3) -> 0.01716 | E5: =IF($A5="","",1*'Material Costs'!$D$2) -> 0.1699 | F5: =IF($A5="","",IF($C5="Bubble Mailer",2,1)*'Material Costs'!$D$6) -> 0.1712 | G5: =IF($A5="","",1*'Material Costs'!$D$7) -> 0.0525 | H5: =IF($A5="","",IF($C5="Bubble Mailer",1,0)*'Material Costs'!$D$5) -> 0 | I5: =IF($A5="","",IF($C5="ESE (Ding Defend)",1,0)*'Material Costs'!$D$4) -> 0.227 | J5: 1.03 | K5: =IF($A5="","",SUM($B5:$J5)) -> 2.01776 | L5: 1.49 | M5: 1.49 | N5: 0 | O5: =IF($A5="","",SUM($L5:$N5)) -> 2.98 | Q5: =IF($A5="","",IF($O5="", "", ROUND($O5*Settings!$B$2+Settings!$B$3,2))) -> 0.69 | R5: 0 | S5: =IF($A5="","",IF($O5="", "", ROUND($O5 - IF($P5<>"",$P5,$Q5) - $R5,2))) -> 2.29 | T5: =IF($A5="","",IF($S5="", "", ROUND($S5 - $K5,2))) -> 0.27 | U5: =IF($A5="","",IF($K5="", "", ROUND((($K5 + Settings!$B$3 + $R5) - IF($M5="",0,$M5))/(1-Settings!$B$2),2))) -> 0.95 | V5: =IF($A5="","",$L5-($L5*Settings!$B$2)-$J5-($B5+SUM($D5:$I5))) -> -0.725185 | W5: =IF($A5="","",(($B5+SUM($D5:$I5)+$J5+Settings!$B$3)/(1-Settings!$B$2))-$M5) -> 1.1817695 | X5: =IF($A5="","",IF($O5="", "", IFERROR($T5/$O5, ""))) -> 0.090604027 | Y5: =IF($A5="","",IF($K5="", "", IFERROR($T5/$K5, ""))) -> 0.13381175 | Z5: =IF($A5="","",IF($O5="", "", IFERROR($Q5/$O5, ""))) -> 0.23154362 | AA5: =IF($A5="","",IF($L5="", "", IFERROR($T5/$L5, ""))) -> 0.18120805 | AE5: =IF($A5="","",IF(OR($AC5="", $AD5=""),"", $AD5-$AC5))
A6: Mookie Betts 2026 Topps Series 1 Orange Diamante #/25 Dodgers SP Parallel | B6: 0.25 | C6: Bubble Mailer | D6: =IF($A6="","",1*'Material Costs'!$D$3) -> 0.01716 | E6: =IF($A6="","",1*'Material Costs'!$D$2) -> 0.1699 | F6: =IF($A6="","",IF($C6="Bubble Mailer",2,1)*'Material Costs'!$D$6) -> 0.3424 | G6: =IF($A6="","",1*'Material Costs'!$D$7) -> 0.0525 | H6: =IF($A6="","",IF($C6="Bubble Mailer",1,0)*'Material Costs'!$D$5) -> 0.1976 | I6: =IF($A6="","",IF($C6="ESE (Ding Defend)",1,0)*'Material Costs'!$D$4) -> 0 | J6: 5.07 | K6: =IF($A6="","",SUM($B6:$J6)) -> 6.09956 | L6: 35 | M6: 5.07 | N6: 0 | O6: =IF($A6="","",SUM($L6:$N6)) -> 40.07 | P6: 5.71 | Q6: =IF($A6="","",IF($O6="", "", ROUND($O6*Settings!$B$2+Settings!$B$3,2))) -> 5.61 | R6: 0 | S6: =IF($A6="","",IF($O6="", "", ROUND($O6 - IF($P6<>"",$P6,$Q6) - $R6,2))) -> 34.36 | T6: =IF($A6="","",IF($S6="", "", ROUND($S6 - $K6,2))) -> 28.26 | U6: =IF($A6="","",IF($K6="", "", ROUND((($K6 + Settings!$B$3 + $R6) - IF($M6="",0,$M6))/(1-Settings!$B$2),2))) -> 1.53 | V6: =IF($A6="","",$L6-($L6*Settings!$B$2)-$J6-($B6+SUM($D6:$I6))) -> 24.26294 | W6: =IF($A6="","",(($B6+SUM($D6:$I6)+$J6+Settings!$B$3)/(1-Settings!$B$2))-$M6) -> 2.3070144 | X6: =IF($A6="","",IF($O6="", "", IFERROR($T6/$O6, ""))) -> 0.70526578 | Y6: =IF($A6="","",IF($K6="", "", IFERROR($T6/$K6, ""))) -> 4.6331211 | Z6: =IF($A6="","",IF($O6="", "", IFERROR($Q6/$O6, ""))) -> 0.14000499 | AA6: =IF($A6="","",IF($L6="", "", IFERROR($T6/$L6, ""))) -> 0.80742857 | AE6: =IF($A6="","",IF(OR($AC6="", $AD6=""),"", $AD6-$AC6))
A7: Shohei Ohtani 2026 Topps Diamante Foil #200 Dodgers MVP Parallel | B7: 0.25 | C7: ESE (Ding Defend) | D7: =IF($A7="","",1*'Material Costs'!$D$3) -> 0.01716 | E7: =IF($A7="","",1*'Material Costs'!$D$2) -> 0.1699 | F7: =IF($A7="","",IF($C7="Bubble Mailer",2,1)*'Material Costs'!$D$6) -> 0.1712 | G7: =IF($A7="","",1*'Material Costs'!$D$7) -> 0.0525 | H7: =IF($A7="","",IF($C7="Bubble Mailer",1,0)*'Material Costs'!$D$5) -> 0 | I7: =IF($A7="","",IF($C7="ESE (Ding Defend)",1,0)*'Material Costs'!$D$4) -> 0.227 | J7: 1.03 | K7: =IF($A7="","",SUM($B7:$J7)) -> 1.91776 | L7: 15 | M7: 1.49 | N7: 0.9 | O7: =IF($A7="","",SUM($L7:$N7)) -> 17.39 | P7: 2.7 | Q7: =IF($A7="","",IF($O7="", "", ROUND($O7*Settings!$B$2+Settings!$B$3,2))) -> 2.6 | R7: 0 | S7: =IF($A7="","",IF($O7="", "", ROUND($O7 - IF($P7<>"",$P7,$Q7) - $R7,2))) -> 14.69 | T7: =IF($A7="","",IF($S7="", "", ROUND($S7 - $K7,2))) -> 12.77 | U7: =IF($A7="","",IF($K7="", "", ROUND((($K7 + Settings!$B$3 + $R7) - IF($M7="",0,$M7))/(1-Settings!$B$2),2))) -> 0.84 | V7: =IF($A7="","",$L7-($L7*Settings!$B$2)-$J7-($B7+SUM($D7:$I7))) -> 11.09474 | W7: =IF($A7="","",(($B7+SUM($D7:$I7)+$J7+Settings!$B$3)/(1-Settings!$B$2))-$M7) -> 1.0664957 | X7: =IF($A7="","",IF($O7="", "", IFERROR($T7/$O7, ""))) -> 0.73433007 | Y7: =IF($A7="","",IF($K7="", "", IFERROR($T7/$K7, ""))) -> 6.6588103 | Z7: =IF($A7="","",IF($O7="", "", IFERROR($Q7/$O7, ""))) -> 0.14951121 | AA7: =IF($A7="","",IF($L7="", "", IFERROR($T7/$L7, ""))) -> 0.85133333 | AE7: =IF($A7="","",IF(OR($AC7="", $AD7=""),"", $AD7-$AC7))
A8: Michael Jordan 1990 SkyBox #41 Chicago Bulls NBA Basketball Card NM | B8: 0.5 | C8: ESE (Ding Defend) | D8: =IF($A8="","",1*'Material Costs'!$D$3) -> 0.01716 | E8: =IF($A8="","",1*'Material Costs'!$D$2) -> 0.1699 | F8: 0 | G8: =IF($A8="","",1*'Material Costs'!$D$7) -> 0.0525 | H8: =IF($A8="","",IF($C8="Bubble Mailer",1,0)*'Material Costs'!$D$5) -> 0 | I8: =IF($A8="","",IF($C8="ESE (Ding Defend)",1,0)*'Material Costs'!$D$4) -> 0.227 | J8: 1.03 | K8: =IF($A8="","",SUM($B8:$J8)) -> 1.99656 | L8: 3.2 | M8: 1.49 | N8: 0.33 | O8: =IF($A8="","",SUM($L8:$N8)) -> 5.02 | P8: 0.97 | Q8: =IF($A8="","",IF($O8="", "", ROUND($O8*Settings!$B$2+Settings!$B$3,2))) -> 0.97 | R8: 0 | S8: =IF($A8="","",IF($O8="", "", ROUND($O8 - IF($P8<>"",$P8,$Q8) - $R8,2))) -> 4.05 | T8: =IF($A8="","",IF($S8="", "", ROUND($S8 - $K8,2))) -> 2.05 | U8: =IF($A8="","",IF($K8="", "", ROUND((($K8 + Settings!$B$3 + $R8) - IF($M8="",0,$M8))/(1-Settings!$B$2),2))) -> 0.93 | V8: =IF($A8="","",$L8-($L8*Settings!$B$2)-$J8-($B8+SUM($D8:$I8))) -> 0.77944 | W8: =IF($A8="","",(($B8+SUM($D8:$I8)+$J8+Settings!$B$3)/(1-Settings!$B$2))-$M8) -> 1.1573314 | X8: =IF($A8="","",IF($O8="", "", IFERROR($T8/$O8, ""))) -> 0.40836653 | Y8: =IF($A8="","",IF($K8="", "", IFERROR($T8/$K8, ""))) -> 1.026766 | Z8: =IF($A8="","",IF($O8="", "", IFERROR($Q8/$O8, ""))) -> 0.19322709 | AA8: =IF($A8="","",IF($L8="", "", IFERROR($T8/$L8, ""))) -> 0.640625 | AE8: =IF($A8="","",IF(OR($AC8="", $AD8=""),"", $AD8-$AC8))
A9: Terrance Ferguson 2025 Rookies & Stars RC Crusade Red Prizm #27 Rams Rookie | B9: 0.25 | C9: ESE (Ding Defend) | D9: =IF($A9="","",1*'Material Costs'!$D$3) -> 0.01716 | E9: =IF($A9="","",1*'Material Costs'!$D$2) -> 0.1699 | F9: 0 | G9: =IF($A9="","",1*'Material Costs'!$D$7) -> 0.0525 | H9: =IF($A9="","",IF($C9="Bubble Mailer",1,0)*'Material Costs'!$D$5) -> 0 | I9: =IF($A9="","",IF($C9="ESE (Ding Defend)",1,0)*'Material Costs'!$D$4) -> 0.227 | J9: 1.03 | K9: =IF($A9="","",SUM($B9:$J9)) -> 1.74656 | L9: 1.95 | M9: 1.49 | N9: 0 | O9: =IF($A9="","",SUM($L9:$N9)) -> 3.44 | Q9: =IF($A9="","",IF($O9="", "", ROUND($O9*Settings!$B$2+Settings!$B$3,2))) -> 0.76 | R9: 0 | S9: =IF($A9="","",IF($O9="", "", ROUND($O9 - IF($P9<>"",$P9,$Q9) - $R9,2))) -> 2.68 | T9: =IF($A9="","",IF($S9="", "", ROUND($S9 - $K9,2))) -> 0.93 | U9: =IF($A9="","",IF($K9="", "", ROUND((($K9 + Settings!$B$3 + $R9) - IF($M9="",0,$M9))/(1-Settings!$B$2),2))) -> 0.64 | V9: =IF($A9="","",$L9-($L9*Settings!$B$2)-$J9-($B9+SUM($D9:$I9))) -> -0.054935 | W9: =IF($A9="","",(($B9+SUM($D9:$I9)+$J9+Settings!$B$3)/(1-Settings!$B$2))-$M9) -> 0.86914697 | X9: =IF($A9="","",IF($O9="", "", IFERROR($T9/$O9, ""))) -> 0.27034884 | Y9: =IF($A9="","",IF($K9="", "", IFERROR($T9/$K9, ""))) -> 0.53247527 | Z9: =IF($A9="","",IF($O9="", "", IFERROR($Q9/$O9, ""))) -> 0.22093023 | AA9: =IF($A9="","",IF($L9="", "", IFERROR($T9/$L9, ""))) -> 0.47692308 | AE9: =IF($A9="","",IF(OR($AC9="", $AD9=""),"", $AD9-$AC9))
A10: Elly De La Cruz 2023 Bowman Chrome Spotlights BS-8 RC Rookie Reds | B10: 0.55 | C10: ESE (Ding Defend) | D10: =IF($A10="","",1*'Material Costs'!$D$3) -> 0.01716 | E10: =IF($A10="","",1*'Material Costs'!$D$2) -> 0.1699 | F10: 0 | G10: =IF($A10="","",1*'Material Costs'!$D$7) -> 0.0525 | H10: =IF($A10="","",IF($C10="Bubble Mailer",1,0)*'Material Costs'!$D$5) -> 0 | I10: =IF($A10="","",IF($C10="ESE (Ding Defend)",1,0)*'Material Costs'!$D$4) -> 0.227 | J10: 1.03 | K10: =IF($A10="","",SUM($B10:$J10)) -> 2.04656 | L10: 6.5 | M10: 1.49 | N10: 0 | O10: =IF($A10="","",SUM($L10:$N10)) -> 7.99 | P10: 1.36 | Q10: =IF($A10="","",IF($O10="", "", ROUND($O10*Settings!$B$2+Settings!$B$3,2))) -> 1.36 | R10: 0 | S10: =IF($A10="","",IF($O10="", "", ROUND($O10 - IF($P10<>"",$P10,$Q10) - $R10,2))) -> 6.63 | T10: =IF($A10="","",IF($S10="", "", ROUND($S10 - $K10,2))) -> 4.58 | U10: =IF($A10="","",IF($K10="", "", ROUND((($K10 + Settings!$B$3 + $R10) - IF($M10="",0,$M10))/(1-Settings!$B$2),2))) -> 0.99 | V10: =IF($A10="","",$L10-($L10*Settings!$B$2)-$J10-($B10+SUM($D10:$I10))) -> 3.59219 | W10: =IF($A10="","",(($B10+SUM($D10:$I10)+$J10+Settings!$B$3)/(1-Settings!$B$2))-$M10) -> 1.2149683 | X10: =IF($A10="","",IF($O10="", "", IFERROR($T10/$O10, ""))) -> 0.57321652 | Y10: =IF($A10="","",IF($K10="", "", IFERROR($T10/$K10, ""))) -> 2.2379016 | Z10: =IF($A10="","",IF($O10="", "", IFERROR($Q10/$O10, ""))) -> 0.17021277 | AA10: =IF($A10="","",IF($L10="", "", IFERROR($T10/$L10, ""))) -> 0.70461538 | AE10: =IF($A10="","",IF(OR($AC10="", $AD10=""),"", $AD10-$AC10))
A11: James Wood RC 2026 Topps 1990 Topps Rookie Insert Nationals | B11: 0.25 | C11: ESE (Ding Defend) | D11: =IF($A11="","",1*'Material Costs'!$D$3) -> 0.01716 | E11: =IF($A11="","",1*'Material Costs'!$D$2) -> 0.1699 | F11: 0 | G11: =IF($A11="","",1*'Material Costs'!$D$7) -> 0.0525 | H11: =IF($A11="","",IF($C11="Bubble Mailer",1,0)*'Material Costs'!$D$5) -> 0 | I11: =IF($A11="","",IF($C11="ESE (Ding Defend)",1,0)*'Material Costs'!$D$4) -> 0.227 | J11: 1.03 | K11: =IF($A11="","",SUM($B11:$J11)) -> 1.74656 | L11: 1.65 | M11: 1.49 | N11: 0 | O11: =IF($A11="","",SUM($L11:$N11)) -> 3.14 | Q11: =IF($A11="","",IF($O11="", "", ROUND($O11*Settings!$B$2+Settings!$B$3,2))) -> 0.72 | R11: 0 | S11: =IF($A11="","",IF($O11="", "", ROUND($O11 - IF($P11<>"",$P11,$Q11) - $R11,2))) -> 2.42 | T11: =IF($A11="","",IF($S11="", "", ROUND($S11 - $K11,2))) -> 0.67 | U11: =IF($A11="","",IF($K11="", "", ROUND((($K11 + Settings!$B$3 + $R11) - IF($M11="",0,$M11))/(1-Settings!$B$2),2))) -> 0.64 | V11: =IF($A11="","",$L11-($L11*Settings!$B$2)-$J11-($B11+SUM($D11:$I11))) -> -0.315185 | W11: =IF($A11="","",(($B11+SUM($D11:$I11)+$J11+Settings!$B$3)/(1-Settings!$B$2))-$M11) -> 0.86914697 | X11: =IF($A11="","",IF($O11="", "", IFERROR($T11/$O11, ""))) -> 0.2133758 | Y11: =IF($A11="","",IF($K11="", "", IFERROR($T11/$K11, ""))) -> 0.38361121 | Z11: =IF($A11="","",IF($O11="", "", IFERROR($Q11/$O11, ""))) -> 0.22929936 | AA11: =IF($A11="","",IF($L11="", "", IFERROR($T11/$L11, ""))) -> 0.40606061 | AE11: =IF($A11="","",IF(OR($AC11="", $AD11=""),"", $AD11-$AC11))
A12: Ronald Acuna Jr 2026 Topps Series 1 Stars Of MLB #SMLB-15 Atlanta Braves | B12: 0.25 | C12: ESE (Ding Defend) | D12: =IF($A12="","",1*'Material Costs'!$D$3) -> 0.01716 | E12: =IF($A12="","",1*'Material Costs'!$D$2) -> 0.1699 | F12: 0 | G12: =IF($A12="","",1*'Material Costs'!$D$7) -> 0.0525 | H12: =IF($A12="","",IF($C12="Bubble Mailer",1,0)*'Material Costs'!$D$5) -> 0 | I12: =IF($A12="","",IF($C12="ESE (Ding Defend)",1,0)*'Material Costs'!$D$4) -> 0.227 | J12: 1.03 | K12: =IF($A12="","",SUM($B12:$J12)) -> 1.74656 | L12: 2.45 | M12: 1.49 | N12: 0 | O12: =IF($A12="","",SUM($L12:$N12)) -> 3.94 | Q12: =IF($A12="","",IF($O12="", "", ROUND($O12*Settings!$B$2+Settings!$B$3,2))) -> 0.82 | R12: 0 | S12: =IF($A12="","",IF($O12="", "", ROUND($O12 - IF($P12<>"",$P12,$Q12) - $R12,2))) -> 3.12 | T12: =IF($A12="","",IF($S12="", "", ROUND($S12 - $K12,2))) -> 1.37 | U12: =IF($A12="","",IF($K12="", "", ROUND((($K12 + Settings!$B$3 + $R12) - IF($M12="",0,$M12))/(1-Settings!$B$2),2))) -> 0.64 | V12: =IF($A12="","",$L12-($L12*Settings!$B$2)-$J12-($B12+SUM($D12:$I12))) -> 0.378815 | W12: =IF($A12="","",(($B12+SUM($D12:$I12)+$J12+Settings!$B$3)/(1-Settings!$B$2))-$M12) -> 0.86914697 | X12: =IF($A12="","",IF($O12="", "", IFERROR($T12/$O12, ""))) -> 0.34771574 | Y12: =IF($A12="","",IF($K12="", "", IFERROR($T12/$K12, ""))) -> 0.78439905 | Z12: =IF($A12="","",IF($O12="", "", IFERROR($Q12/$O12, ""))) -> 0.20812183 | AA12: =IF($A12="","",IF($L12="", "", IFERROR($T12/$L12, ""))) -> 0.55918367 | AE12: =IF($A12="","",IF(OR($AC12="", $AD12=""),"", $AD12-$AC12))
A13: Shohei Ohtani 2025 Topps Summer Superstars #SS-19 MLB Dodgers Insert | B13: 0.34 | C13: ESE (Ding Defend) | D13: =IF($A13="","",1*'Material Costs'!$D$3) -> 0.01716 | E13: =IF($A13="","",1*'Material Costs'!$D$2) -> 0.1699 | F13: 0 | G13: =IF($A13="","",1*'Material Costs'!$D$7) -> 0.0525 | H13: =IF($A13="","",IF($C13="Bubble Mailer",1,0)*'Material Costs'!$D$5) -> 0 | I13: =IF($A13="","",IF($C13="ESE (Ding Defend)",1,0)*'Material Costs'!$D$4) -> 0.227 | J13: 1.03 | K13: =IF($A13="","",SUM($B13:$J13)) -> 1.83656 | L13: 2.25 | M13: 1.49 | N13: 0.17 | O13: =IF($A13="","",SUM($L13:$N13)) -> 3.91 | P13: 0.82 | Q13: =IF($A13="","",IF($O13="", "", ROUND($O13*Settings!$B$2+Settings!$B$3,2))) -> 0.82 | R13: 0 | S13: =IF($A13="","",IF($O13="", "", ROUND($O13 - IF($P13<>"",$P13,$Q13) - $R13,2))) -> 3.09 | T13: =IF($A13="","",IF($S13="", "", ROUND($S13 - $K13,2))) -> 1.25 | U13: =IF($A13="","",IF($K13="", "", ROUND((($K13 + Settings!$B$3 + $R13) - IF($M13="",0,$M13))/(1-Settings!$B$2),2))) -> 0.75 | V13: =IF($A13="","",$L13-($L13*Settings!$B$2)-$J13-($B13+SUM($D13:$I13))) -> 0.115315 | W13: =IF($A13="","",(($B13+SUM($D13:$I13)+$J13+Settings!$B$3)/(1-Settings!$B$2))-$M13) -> 0.97289337 | X13: =IF($A13="","",IF($O13="", "", IFERROR($T13/$O13, ""))) -> 0.31969309 | Y13: =IF($A13="","",IF($K13="", "", IFERROR($T13/$K13, ""))) -> 0.68062029 | Z13: =IF($A13="","",IF($O13="", "", IFERROR($Q13/$O13, ""))) -> 0.20971867 | AA13: =IF($A13="","",IF($L13="", "", IFERROR($T13/$L13, ""))) -> 0.55555556 | AE13: =IF($A13="","",IF(OR($AC13="", $AD13=""),"", $AD13-$AC13))
A14: 2025 Bowman Draft Mojo Chrome Tyler Bremner 1st BDC-37 Angels | B14: 1.85 | C14: ESE (Ding Defend) | D14: =IF($A14="","",1*'Material Costs'!$D$3) -> 0.01716 | E14: =IF($A14="","",1*'Material Costs'!$D$2) -> 0.1699 | F14: 0 | G14: =IF($A14="","",1*'Material Costs'!$D$7) -> 0.0525 | H14: =IF($A14="","",IF($C14="Bubble Mailer",1,0)*'Material Costs'!$D$5) -> 0 | I14: =IF($A14="","",IF($C14="ESE (Ding Defend)",1,0)*'Material Costs'!$D$4) -> 0.227 | J14: 1.03 | K14: =IF($A14="","",SUM($B14:$J14)) -> 3.34656 | L14: 3.5 | M14: 1.49 | O14: =IF($A14="","",SUM($L14:$N14)) -> 4.99 | Q14: =IF($A14="","",IF($O14="", "", ROUND($O14*Settings!$B$2+Settings!$B$3,2))) -> 0.96 | R14: 0 | S14: =IF($A14="","",IF($O14="", "", ROUND($O14 - IF($P14<>"",$P14,$Q14) - $R14,2))) -> 4.03 | T14: =IF($A14="","",IF($S14="", "", ROUND($S14 - $K14,2))) -> 0.68 | U14: =IF($A14="","",IF($K14="", "", ROUND((($K14 + Settings!$B$3 + $R14) - IF($M14="",0,$M14))/(1-Settings!$B$2),2))) -> 2.49 | V14: =IF($A14="","",$L14-($L14*Settings!$B$2)-$J14-($B14+SUM($D14:$I14))) -> -0.31031 | W14: =IF($A14="","",(($B14+SUM($D14:$I14)+$J14+Settings!$B$3)/(1-Settings!$B$2))-$M14) -> 2.7135274 | X14: =IF($A14="","",IF($O14="", "", IFERROR($T14/$O14, ""))) -> 0.13627255 | Y14: =IF($A14="","",IF($K14="", "", IFERROR($T14/$K14, ""))) -> 0.20319373 | Z14: =IF($A14="","",IF($O14="", "", IFERROR($Q14/$O14, ""))) -> 0.19238477 | AA14: =IF($A14="","",IF($L14="", "", IFERROR($T14/$L14, ""))) -> 0.19428571 | AE14: =IF($A14="","",IF(OR($AC14="", $AD14=""),"", $AD14-$AC14))
A15: Brock Bowers 2024 Donruss Optic Pink Velocity Rated Rookie RC #215 Raiders | B15: 0 | C15: ESE (Ding Defend) | D15: =IF($A15="","",1*'Material Costs'!$D$3) -> 0.01716 | E15: =IF($A15="","",1*'Material Costs'!$D$2) -> 0.1699 | F15: 0 | G15: =IF($A15="","",1*'Material Costs'!$D$7) -> 0.0525 | H15: =IF($A15="","",IF($C15="Bubble Mailer",1,0)*'Material Costs'!$D$5) -> 0 | I15: =IF($A15="","",IF($C15="ESE (Ding Defend)",1,0)*'Material Costs'!$D$4) -> 0.227 | J15: 1.03 | K15: =IF($A15="","",SUM($B15:$J15)) -> 1.49656 | L15: 5.99 | M15: 0 | O15: =IF($A15="","",SUM($L15:$N15)) -> 5.99 | Q15: =IF($A15="","",IF($O15="", "", ROUND($O15*Settings!$B$2+Settings!$B$3,2))) -> 1.09 | R15: 0 | S15: =IF($A15="","",IF($O15="", "", ROUND($O15 - IF($P15<>"",$P15,$Q15) - $R15,2))) -> 4.9 | T15: =IF($A15="","",IF($S15="", "", ROUND($S15 - $K15,2))) -> 3.4 | U15: =IF($A15="","",IF($K15="", "", ROUND((($K15 + Settings!$B$3 + $R15) - IF($M15="",0,$M15))/(1-Settings!$B$2),2))) -> 2.07 | V15: =IF($A15="","",$L15-($L15*Settings!$B$2)-$J15-($B15+SUM($D15:$I15))) -> 3.699765 | W15: =IF($A15="","",(($B15+SUM($D15:$I15)+$J15+Settings!$B$3)/(1-Settings!$B$2))-$M15) -> 2.0709625 | X15: =IF($A15="","",IF($O15="", "", IFERROR($T15/$O15, ""))) -> 0.56761269 | Y15: =IF($A15="","",IF($K15="", "", IFERROR($T15/$K15, ""))) -> 2.2718768 | Z15: =IF($A15="","",IF($O15="", "", IFERROR($Q15/$O15, ""))) -> 0.18196995 | AA15: =IF($A15="","",IF($L15="", "", IFERROR($T15/$L15, ""))) -> 0.56761269 | AE15: =IF($A15="","",IF(OR($AC15="", $AD15=""),"", $AD15-$AC15))
A16: Jacob Melton 2026 Topps RC Spring Training Foil #148 Astros Rookie | B16: 0.25 | C16: ESE (Ding Defend) | D16: =IF($A16="","",1*'Material Costs'!$D$3) -> 0.01716 | E16: =IF($A16="","",1*'Material Costs'!$D$2) -> 0.1699 | F16: 0 | G16: =IF($A16="","",1*'Material Costs'!$D$7) -> 0.0525 | H16: =IF($A16="","",IF($C16="Bubble Mailer",1,0)*'Material Costs'!$D$5) -> 0 | I16: =IF($A16="","",IF($C16="ESE (Ding Defend)",1,0)*'Material Costs'!$D$4) -> 0.227 | J16: 1.03 | K16: =IF($A16="","",SUM($B16:$J16)) -> 1.74656 | L16: 3.99 | M16: 0 | O16: =IF($A16="","",SUM($L16:$N16)) -> 3.99 | Q16: =IF($A16="","",IF($O16="", "", ROUND($O16*Settings!$B$2+Settings!$B$3,2))) -> 0.83 | R16: 0 | S16: =IF($A16="","",IF($O16="", "", ROUND($O16 - IF($P16<>"",$P16,$Q16) - $R16,2))) -> 3.16 | T16: =IF($A16="","",IF($S16="", "", ROUND($S16 - $K16,2))) -> 1.41 | U16: =IF($A16="","",IF($K16="", "", ROUND((($K16 + Settings!$B$3 + $R16) - IF($M16="",0,$M16))/(1-Settings!$B$2),2))) -> 2.36 | V16: =IF($A16="","",$L16-($L16*Settings!$B$2)-$J16-($B16+SUM($D16:$I16))) -> 1.714765 | W16: =IF($A16="","",(($B16+SUM($D16:$I16)+$J16+Settings!$B$3)/(1-Settings!$B$2))-$M16) -> 2.359147 | X16: =IF($A16="","",IF($O16="", "", IFERROR($T16/$O16, ""))) -> 0.35338346 | Y16: =IF($A16="","",IF($K16="", "", IFERROR($T16/$K16, ""))) -> 0.80730121 | Z16: =IF($A16="","",IF($O16="", "", IFERROR($Q16/$O16, ""))) -> 0.20802005 | AA16: =IF($A16="","",IF($L16="", "", IFERROR($T16/$L16, ""))) -> 0.35338346 | AE16: =IF($A16="","",IF(OR($AC16="", $AD16=""),"", $AD16-$AC16))
A17: Victor Wembanyama RC 2023-24 Panini NBA Hoops #277 Rookie Card Spurs Base | B17: 0 | C17: ESE (Ding Defend) | D17: =IF($A17="","",1*'Material Costs'!$D$3) -> 0.01716 | E17: =IF($A17="","",1*'Material Costs'!$D$2) -> 0.1699 | F17: 0 | G17: =IF($A17="","",1*'Material Costs'!$D$7) -> 0.0525 | H17: =IF($A17="","",IF($C17="Bubble Mailer",1,0)*'Material Costs'!$D$5) -> 0 | I17: =IF($A17="","",IF($C17="ESE (Ding Defend)",1,0)*'Material Costs'!$D$4) -> 0.227 | J17: 1.03 | K17: =IF($A17="","",SUM($B17:$J17)) -> 1.49656 | L17: 4 | M17: 0 | N17: 0.33 | O17: 4 | P17: 0.87 | Q17: 0.87 | R17: 0 | S17: =IF($A17="","",IF($O17="", "", ROUND($O17 - IF($P17<>"",$P17,$Q17) - $R17,2))) -> 3.13 | T17: =IF($A17="","",IF($S17="", "", ROUND($S17 - $K17,2))) -> 1.63 | U17: =IF($A17="","",IF($K17="", "", ROUND((($K17 + Settings!$B$3 + $R17) - IF($M17="",0,$M17))/(1-Settings!$B$2),2))) -> 2.07 | V17: =IF($A17="","",$L17-($L17*Settings!$B$2)-$J17-($B17+SUM($D17:$I17))) -> 1.97344 | W17: =IF($A17="","",(($B17+SUM($D17:$I17)+$J17+Settings!$B$3)/(1-Settings!$B$2))-$M17) -> 2.0709625 | X17: =IF($A17="","",IF($O17="", "", IFERROR($T17/$O17, ""))) -> 0.4075 | Y17: =IF($A17="","",IF($K17="", "", IFERROR($T17/$K17, ""))) -> 1.0891645 | Z17: =IF($A17="","",IF($O17="", "", IFERROR($Q17/$O17, ""))) -> 0.2175 | AA17: =IF($A17="","",IF($L17="", "", IFERROR($T17/$L17, ""))) -> 0.4075 | AE17: =IF($A17="","",IF(OR($AC17="", $AD17=""),"", $AD17-$AC17))
A18: Kevin McGonigle 2025 Bowman 1st Mojo Refractor #BCP-79 Chrome Prospect Tigers RC | B18: 0 | C18: ESE (Ding Defend) | D18: =IF($A18="","",1*'Material Costs'!$D$3) -> 0.01716 | E18: =IF($A18="","",1*'Material Costs'!$D$2) -> 0.1699 | F18: 0 | G18: =IF($A18="","",1*'Material Costs'!$D$7) -> 0.0525 | H18: =IF($A18="","",IF($C18="Bubble Mailer",1,0)*'Material Costs'!$D$5) -> 0 | I18: =IF($A18="","",IF($C18="ESE (Ding Defend)",1,0)*'Material Costs'!$D$4) -> 0.227 | J18: 1.03 | K18: =IF($A18="","",SUM($B18:$J18)) -> 1.49656 | L18: 6.5 | M18: 0 | N18: 0.46 | O18: =IF($A18="","",SUM($L18:$N18)) -> 6.96 | P18: 1.22 | Q18: =IF($A18="","",IF($O18="", "", ROUND($O18*Settings!$B$2+Settings!$B$3,2))) -> 1.22 | R18: 0 | S18: =IF($A18="","",IF($O18="", "", ROUND($O18 - IF($P18<>"",$P18,$Q18) - $R18,2))) -> 5.74 | T18: =IF($A18="","",IF($S18="", "", ROUND($S18 - $K18,2))) -> 4.24 | U18: =IF($A18="","",IF($K18="", "", ROUND((($K18 + Settings!$B$3 + $R18) - IF($M18="",0,$M18))/(1-Settings!$B$2),2))) -> 2.07 | V18: =IF($A18="","",$L18-($L18*Settings!$B$2)-$J18-($B18+SUM($D18:$I18))) -> 4.14219 | W18: =IF($A18="","",(($B18+SUM($D18:$I18)+$J18+Settings!$B$3)/(1-Settings!$B$2))-$M18) -> 2.0709625 | X18: =IF($A18="","",IF($O18="", "", IFERROR($T18/$O18, ""))) -> 0.6091954 | Y18: =IF($A18="","",IF($K18="", "", IFERROR($T18/$K18, ""))) -> 2.8331641 | Z18: =IF($A18="","",IF($O18="", "", IFERROR($Q18/$O18, ""))) -> 0.17528736 | AA18: =IF($A18="","",IF($L18="", "", IFERROR($T18/$L18, ""))) -> 0.65230769 | AE18: =IF($A18="","",IF(OR($AC18="", $AD18=""),"", $AD18-$AC18))
A19: Shohei Ohtani 2025 Topps Series 2 Base #400 Los Angeles Dodgers | B19: 0.25 | C19: ESE (Ding Defend) | D19: =IF($A19="","",1*'Material Costs'!$D$3) -> 0.01716 | E19: =IF($A19="","",1*'Material Costs'!$D$2) -> 0.1699 | F19: 0 | G19: =IF($A19="","",1*'Material Costs'!$D$7) -> 0.0525 | H19: =IF($A19="","",IF($C19="Bubble Mailer",1,0)*'Material Costs'!$D$5) -> 0 | I19: =IF($A19="","",IF($C19="ESE (Ding Defend)",1,0)*'Material Costs'!$D$4) -> 0.227 | J19: 1.03 | K19: =IF($A19="","",SUM($B19:$J19)) -> 1.74656 | L19: 1.99 | M19: 0 | O19: =IF($A19="","",SUM($L19:$N19)) -> 1.99 | Q19: =IF($A19="","",IF($O19="", "", ROUND($O19*Settings!$B$2+Settings!$B$3,2))) -> 0.56 | R19: 0 | S19: =IF($A19="","",IF($O19="", "", ROUND($O19 - IF($P19<>"",$P19,$Q19) - $R19,2))) -> 1.43 | T19: =IF($A19="","",IF($S19="", "", ROUND($S19 - $K19,2))) -> -0.32 | U19: =IF($A19="","",IF($K19="", "", ROUND((($K19 + Settings!$B$3 + $R19) - IF($M19="",0,$M19))/(1-Settings!$B$2),2))) -> 2.36 | V19: =IF($A19="","",$L19-($L19*Settings!$B$2)-$J19-($B19+SUM($D19:$I19))) -> -0.020235 | W19: =IF($A19="","",(($B19+SUM($D19:$I19)+$J19+Settings!$B$3)/(1-Settings!$B$2))-$M19) -> 2.359147 | X19: =IF($A19="","",IF($O19="", "", IFERROR($T19/$O19, ""))) -> -0.16080402 | Y19: =IF($A19="","",IF($K19="", "", IFERROR($T19/$K19, ""))) -> -0.1832173 | Z19: =IF($A19="","",IF($O19="", "", IFERROR($Q19/$O19, ""))) -> 0.28140704 | AA19: =IF($A19="","",IF($L19="", "", IFERROR($T19/$L19, ""))) -> -0.16080402 | AE19: =IF($A19="","",IF(OR($AC19="", $AD19=""),"", $AD19-$AC19))
A20: 2025 Topps Series 2 - 1990 Topps Baseball Cal Raleigh #90B2-13 | B20: 0 | C20: ESE (Ding Defend) | D20: =IF($A20="","",1*'Material Costs'!$D$3) -> 0.01716 | E20: =IF($A20="","",1*'Material Costs'!$D$2) -> 0.1699 | F20: 0 | G20: =IF($A20="","",1*'Material Costs'!$D$7) -> 0.0525 | H20: =IF($A20="","",IF($C20="Bubble Mailer",1,0)*'Material Costs'!$D$5) -> 0 | I20: =IF($A20="","",IF($C20="ESE (Ding Defend)",1,0)*'Material Costs'!$D$4) -> 0.227 | J20: 1.03 | K20: =IF($A20="","",SUM($B20:$J20)) -> 1.49656 | L20: 2.25 | M20: 0 | O20: =IF($A20="","",SUM($L20:$N20)) -> 2.25 | Q20: =IF($A20="","",IF($O20="", "", ROUND($O20*Settings!$B$2+Settings!$B$3,2))) -> 0.6 | R20: 0 | S20: =IF($A20="","",IF($O20="", "", ROUND($O20 - IF($P20<>"",$P20,$Q20) - $R20,2))) -> 1.65 | T20: =IF($A20="","",IF($S20="", "", ROUND($S20 - $K20,2))) -> 0.15 | U20: =IF($A20="","",IF($K20="", "", ROUND((($K20 + Settings!$B$3 + $R20) - IF($M20="",0,$M20))/(1-Settings!$B$2),2))) -> 2.07 | V20: =IF($A20="","",$L20-($L20*Settings!$B$2)-$J20-($B20+SUM($D20:$I20))) -> 0.455315 | W20: =IF($A20="","",(($B20+SUM($D20:$I20)+$J20+Settings!$B$3)/(1-Settings!$B$2))-$M20) -> 2.0709625 | X20: =IF($A20="","",IF($O20="", "", IFERROR($T20/$O20, ""))) -> 0.066666667 | Y20: =IF($A20="","",IF($K20="", "", IFERROR($T20/$K20, ""))) -> 0.10022986 | Z20: =IF($A20="","",IF($O20="", "", IFERROR($Q20/$O20, ""))) -> 0.26666667 | AA20: =IF($A20="","",IF($L20="", "", IFERROR($T20/$L20, ""))) -> 0.066666667 | AE20: =IF($A20="","",IF(OR($AC20="", $AD20=""),"", $AD20-$AC20))
A21: 2025 Topps Series 2 - 1990 Topps Chrome Silver Pack All-Stars Nolan Ryan... | B21: 0 | C21: ESE (Ding Defend) | D21: =IF($A21="","",1*'Material Costs'!$D$3) -> 0.01716 | E21: =IF($A21="","",1*'Material Costs'!$D$2) -> 0.1699 | F21: 0 | G21: =IF($A21="","",1*'Material Costs'!$D$7) -> 0.0525 | H21: =IF($A21="","",IF($C21="Bubble Mailer",1,0)*'Material Costs'!$D$5) -> 0 | I21: =IF($A21="","",IF($C21="ESE (Ding Defend)",1,0)*'Material Costs'!$D$4) -> 0.227 | J21: 1.03 | K21: =IF($A21="","",SUM($B21:$J21)) -> 1.49656 | L21: 2.99 | M21: 0 | O21: =IF($A21="","",SUM($L21:$N21)) -> 2.99 | Q21: =IF($A21="","",IF($O21="", "", ROUND($O21*Settings!$B$2+Settings!$B$3,2))) -> 0.7 | R21: 0 | S21: =IF($A21="","",IF($O21="", "", ROUND($O21 - IF($P21<>"",$P21,$Q21) - $R21,2))) -> 2.29 | T21: =IF($A21="","",IF($S21="", "", ROUND($S21 - $K21,2))) -> 0.79 | U21: =IF($A21="","",IF($K21="", "", ROUND((($K21 + Settings!$B$3 + $R21) - IF($M21="",0,$M21))/(1-Settings!$B$2),2))) -> 2.07 | V21: =IF($A21="","",$L21-($L21*Settings!$B$2)-$J21-($B21+SUM($D21:$I21))) -> 1.097265 | W21: =IF($A21="","",(($B21+SUM($D21:$I21)+$J21+Settings!$B$3)/(1-Settings!$B$2))-$M21) -> 2.0709625 | X21: =IF($A21="","",IF($O21="", "", IFERROR($T21/$O21, ""))) -> 0.26421405 | Y21: =IF($A21="","",IF($K21="", "", IFERROR($T21/$K21, ""))) -> 0.52787727 | Z21: =IF($A21="","",IF($O21="", "", IFERROR($Q21/$O21, ""))) -> 0.23411371 | AA21: =IF($A21="","",IF($L21="", "", IFERROR($T21/$L21, ""))) -> 0.26421405 | AE21: =IF($A21="","",IF(OR($AC21="", $AD21=""),"", $AD21-$AC21))
A22: 2025 Topps Shohei Ohtani OPS Leaders #OPS-2 Dodgers | B22: 0.25 | C22: ESE (Ding Defend) | D22: =IF($A22="","",1*'Material Costs'!$D$3) -> 0.01716 | E22: =IF($A22="","",1*'Material Costs'!$D$2) -> 0.1699 | F22: 0 | G22: =IF($A22="","",1*'Material Costs'!$D$7) -> 0.0525 | H22: =IF($A22="","",IF($C22="Bubble Mailer",1,0)*'Material Costs'!$D$5) -> 0 | I22: =IF($A22="","",IF($C22="ESE (Ding Defend)",1,0)*'Material Costs'!$D$4) -> 0.227 | J22: 1.03 | K22: =IF($A22="","",SUM($B22:$J22)) -> 1.74656 | L22: 2.99 | M22: 0 | O22: =IF($A22="","",SUM($L22:$N22)) -> 2.99 | Q22: =IF($A22="","",IF($O22="", "", ROUND($O22*Settings!$B$2+Settings!$B$3,2))) -> 0.7 | R22: 0 | S22: =IF($A22="","",IF($O22="", "", ROUND($O22 - IF($P22<>"",$P22,$Q22) - $R22,2))) -> 2.29 | T22: =IF($A22="","",IF($S22="", "", ROUND($S22 - $K22,2))) -> 0.54 | U22: =IF($A22="","",IF($K22="", "", ROUND((($K22 + Settings!$B$3 + $R22) - IF($M22="",0,$M22))/(1-Settings!$B$2),2))) -> 2.36 | V22: =IF($A22="","",$L22-($L22*Settings!$B$2)-$J22-($B22+SUM($D22:$I22))) -> 0.847265 | W22: =IF($A22="","",(($B22+SUM($D22:$I22)+$J22+Settings!$B$3)/(1-Settings!$B$2))-$M22) -> 2.359147 | X22: =IF($A22="","",IF($O22="", "", IFERROR($T22/$O22, ""))) -> 0.18060201 | Y22: =IF($A22="","",IF($K22="", "", IFERROR($T22/$K22, ""))) -> 0.30917919 | Z22: =IF($A22="","",IF($O22="", "", IFERROR($Q22/$O22, ""))) -> 0.23411371 | AA22: =IF($A22="","",IF($L22="", "", IFERROR($T22/$L22, ""))) -> 0.18060201 | AE22: =IF($A22="","",IF(OR($AC22="", $AD22=""),"", $AD22-$AC22))
A23: 2026 Topps Series 1 Baseball Bryan Woo #62 Spring Training Foil | B23: 0.25 | C23: ESE (Ding Defend) | D23: =IF($A23="","",1*'Material Costs'!$D$3) -> 0.01716 | E23: =IF($A23="","",1*'Material Costs'!$D$2) -> 0.1699 | F23: 0 | G23: =IF($A23="","",1*'Material Costs'!$D$7) -> 0.0525 | H23: =IF($A23="","",IF($C23="Bubble Mailer",1,0)*'Material Costs'!$D$5) -> 0 | I23: =IF($A23="","",IF($C23="ESE (Ding Defend)",1,0)*'Material Costs'!$D$4) -> 0.227 | J23: 1.03 | K23: =IF($A23="","",SUM($B23:$J23)) -> 1.74656 | L23: 2.99 | M23: 0 | O23: =IF($A23="","",SUM($L23:$N23)) -> 2.99 | Q23: =IF($A23="","",IF($O23="", "", ROUND($O23*Settings!$B$2+Settings!$B$3,2))) -> 0.7 | R23: 0 | S23: =IF($A23="","",IF($O23="", "", ROUND($O23 - IF($P23<>"",$P23,$Q23) - $R23,2))) -> 2.29 | T23: =IF($A23="","",IF($S23="", "", ROUND($S23 - $K23,2))) -> 0.54 | U23: =IF($A23="","",IF($K23="", "", ROUND((($K23 + Settings!$B$3 + $R23) - IF($M23="",0,$M23))/(1-Settings!$B$2),2))) -> 2.36 | V23: =IF($A23="","",$L23-($L23*Settings!$B$2)-$J23-($B23+SUM($D23:$I23))) -> 0.847265 | W23: =IF($A23="","",(($B23+SUM($D23:$I23)+$J23+Settings!$B$3)/(1-Settings!$B$2))-$M23) -> 2.359147 | X23: =IF($A23="","",IF($O23="", "", IFERROR($T23/$O23, ""))) -> 0.18060201 | Y23: =IF($A23="","",IF($K23="", "", IFERROR($T23/$K23, ""))) -> 0.30917919 | Z23: =IF($A23="","",IF($O23="", "", IFERROR($Q23/$O23, ""))) -> 0.23411371 | AA23: =IF($A23="","",IF($L23="", "", IFERROR($T23/$L23, ""))) -> 0.18060201 | AE23: =IF($A23="","",IF(OR($AC23="", $AD23=""),"", $AD23-$AC23))
C24: ESE (Ding Defend) | D24: =IF($A24="","",1*'Material Costs'!$D$3) | E24: =IF($A24="","",1*'Material Costs'!$D$2) | F24: =IF($A24="","",IF($C24="Bubble Mailer",2,1)*'Material Costs'!$D$6) | G24: =IF($A24="","",1*'Material Costs'!$D$7) | H24: =IF($A24="","",IF($C24="Bubble Mailer",1,0)*'Material Costs'!$D$5) | I24: =IF($A24="","",IF($C24="ESE (Ding Defend)",1,0)*'Material Costs'!$D$4) | K24: =IF($A24="","",SUM($B24:$J24)) | O24: =IF($A24="","",SUM($L24:$N24)) | Q24: =IF($A24="","",IF($O24="", "", ROUND($O24*Settings!$B$2+Settings!$B$3,2))) | R24: =IF($A24="","",IF($L24="", "", Settings!$B$4)) | S24: =IF($A24="","",IF($O24="", "", ROUND($O24 - IF($P24<>"",$P24,$Q24) - $R24,2))) | T24: =IF($A24="","",IF($S24="", "", ROUND($S24 - $K24,2))) | U24: =IF($A24="","",IF($K24="", "", ROUND((($K24 + Settings!$B$3 + $R24) - IF($M24="",0,$M24))/(1-Settings!$B$2),2))) | V24: =IF($A24="","",$L24-($L24*Settings!$B$2)-$J24-($B24+SUM($D24:$I24))) | W24: =IF($A24="","",(($B24+SUM($D24:$I24)+$J24+Settings!$B$3)/(1-Settings!$B$2))-$M24) | X24: =IF($A24="","",IF($O24="", "", IFERROR($T24/$O24, ""))) | Y24: =IF($A24="","",IF($K24="", "", IFERROR($T24/$K24, ""))) | Z24: =IF($A24="","",IF($O24="", "", IFERROR($Q24/$O24, ""))) | AA24: =IF($A24="","",IF($L24="", "", IFERROR($T24/$L24, ""))) | AE24: =IF($A24="","",IF(OR($AC24="", $AD24=""),"", $AD24-$AC24))
C25: ESE (Ding Defend) | D25: =IF($A25="","",1*'Material Costs'!$D$3) | E25: =IF($A25="","",1*'Material Costs'!$D$2) | F25: =IF($A25="","",IF($C25="Bubble Mailer",2,1)*'Material Costs'!$D$6) | G25: =IF($A25="","",1*'Material Costs'!$D$7) | H25: =IF($A25="","",IF($C25="Bubble Mailer",1,0)*'Material Costs'!$D$5) | I25: =IF($A25="","",IF($C25="ESE (Ding Defend)",1,0)*'Material Costs'!$D$4) | K25: =IF($A25="","",SUM($B25:$J25)) | O25: =IF($A25="","",SUM($L25:$N25)) | Q25: =IF($A25="","",IF($O25="", "", ROUND($O25*Settings!$B$2+Settings!$B$3,2))) | R25: =IF($A25="","",IF($L25="", "", Settings!$B$4)) | S25: =IF($A25="","",IF($O25="", "", ROUND($O25 - IF($P25<>"",$P25,$Q25) - $R25,2))) | T25: =IF($A25="","",IF($S25="", "", ROUND($S25 - $K25,2))) | U25: =IF($A25="","",IF($K25="", "", ROUND((($K25 + Settings!$B$3 + $R25) - IF($M25="",0,$M25))/(1-Settings!$B$2),2))) | V25: =IF($A25="","",$L25-($L25*Settings!$B$2)-$J25-($B25+SUM($D25:$I25))) | W25: =IF($A25="","",(($B25+SUM($D25:$I25)+$J25+Settings!$B$3)/(1-Settings!$B$2))-$M25) | X25: =IF($A25="","",IF($O25="", "", IFERROR($T25/$O25, ""))) | Y25: =IF($A25="","",IF($K25="", "", IFERROR($T25/$K25, ""))) | Z25: =IF($A25="","",IF($O25="", "", IFERROR($Q25/$O25, ""))) | AA25: =IF($A25="","",IF($L25="", "", IFERROR($T25/$L25, ""))) | AE25: =IF($A25="","",IF(OR($AC25="", $AD25=""),"", $AD25-$AC25))
C26: ESE (Ding Defend) | D26: =IF($A26="","",1*'Material Costs'!$D$3) | E26: =IF($A26="","",1*'Material Costs'!$D$2) | F26: =IF($A26="","",IF($C26="Bubble Mailer",2,1)*'Material Costs'!$D$6) | G26: =IF($A26="","",1*'Material Costs'!$D$7) | H26: =IF($A26="","",IF($C26="Bubble Mailer",1,0)*'Material Costs'!$D$5) | I26: =IF($A26="","",IF($C26="ESE (Ding Defend)",1,0)*'Material Costs'!$D$4) | K26: =IF($A26="","",SUM($B26:$J26)) | O26: =IF($A26="","",SUM($L26:$N26)) | Q26: =IF($A26="","",IF($O26="", "", ROUND($O26*Settings!$B$2+Settings!$B$3,2))) | R26: =IF($A26="","",IF($L26="", "", Settings!$B$4)) | S26: =IF($A26="","",IF($O26="", "", ROUND($O26 - IF($P26<>"",$P26,$Q26) - $R26,2))) | T26: =IF($A26="","",IF($S26="", "", ROUND($S26 - $K26,2))) | U26: =IF($A26="","",IF($K26="", "", ROUND((($K26 + Settings!$B$3 + $R26) - IF($M26="",0,$M26))/(1-Settings!$B$2),2))) | V26: =IF($A26="","",$L26-($L26*Settings!$B$2)-$J26-($B26+SUM($D26:$I26))) | W26: =IF($A26="","",(($B26+SUM($D26:$I26)+$J26+Settings!$B$3)/(1-Settings!$B$2))-$M26) | X26: =IF($A26="","",IF($O26="", "", IFERROR($T26/$O26, ""))) | Y26: =IF($A26="","",IF($K26="", "", IFERROR($T26/$K26, ""))) | Z26: =IF($A26="","",IF($O26="", "", IFERROR($Q26/$O26, ""))) | AA26: =IF($A26="","",IF($L26="", "", IFERROR($T26/$L26, ""))) | AE26: =IF($A26="","",IF(OR($AC26="", $AD26=""),"", $AD26-$AC26))
C27: ESE (Ding Defend) | D27: =IF($A27="","",1*'Material Costs'!$D$3) | E27: =IF($A27="","",1*'Material Costs'!$D$2) | F27: =IF($A27="","",IF($C27="Bubble Mailer",2,1)*'Material Costs'!$D$6) | G27: =IF($A27="","",1*'Material Costs'!$D$7) | H27: =IF($A27="","",IF($C27="Bubble Mailer",1,0)*'Material Costs'!$D$5) | I27: =IF($A27="","",IF($C27="ESE (Ding Defend)",1,0)*'Material Costs'!$D$4) | K27: =IF($A27="","",SUM($B27:$J27)) | O27: =IF($A27="","",SUM($L27:$N27)) | Q27: =IF($A27="","",IF($O27="", "", ROUND($O27*Settings!$B$2+Settings!$B$3,2))) | R27: =IF($A27="","",IF($L27="", "", Settings!$B$4)) | S27: =IF($A27="","",IF($O27="", "", ROUND($O27 - IF($P27<>"",$P27,$Q27) - $R27,2))) | T27: =IF($A27="","",IF($S27="", "", ROUND($S27 - $K27,2))) | U27: =IF($A27="","",IF($K27="", "", ROUND((($K27 + Settings!$B$3 + $R27) - IF($M27="",0,$M27))/(1-Settings!$B$2),2))) | V27: =IF($A27="","",$L27-($L27*Settings!$B$2)-$J27-($B27+SUM($D27:$I27))) | W27: =IF($A27="","",(($B27+SUM($D27:$I27)+$J27+Settings!$B$3)/(1-Settings!$B$2))-$M27) | X27: =IF($A27="","",IF($O27="", "", IFERROR($T27/$O27, ""))) | Y27: =IF($A27="","",IF($K27="", "", IFERROR($T27/$K27, ""))) | Z27: =IF($A27="","",IF($O27="", "", IFERROR($Q27/$O27, ""))) | AA27: =IF($A27="","",IF($L27="", "", IFERROR($T27/$L27, ""))) | AE27: =IF($A27="","",IF(OR($AC27="", $AD27=""),"", $AD27-$AC27))
C28: ESE (Ding Defend) | D28: =IF($A28="","",1*'Material Costs'!$D$3) | E28: =IF($A28="","",1*'Material Costs'!$D$2) | F28: =IF($A28="","",IF($C28="Bubble Mailer",2,1)*'Material Costs'!$D$6) | G28: =IF($A28="","",1*'Material Costs'!$D$7) | H28: =IF($A28="","",IF($C28="Bubble Mailer",1,0)*'Material Costs'!$D$5) | I28: =IF($A28="","",IF($C28="ESE (Ding Defend)",1,0)*'Material Costs'!$D$4) | K28: =IF($A28="","",SUM($B28:$J28)) | O28: =IF($A28="","",SUM($L28:$N28)) | Q28: =IF($A28="","",IF($O28="", "", ROUND($O28*Settings!$B$2+Settings!$B$3,2))) | R28: =IF($A28="","",IF($L28="", "", Settings!$B$4)) | S28: =IF($A28="","",IF($O28="", "", ROUND($O28 - IF($P28<>"",$P28,$Q28) - $R28,2))) | T28: =IF($A28="","",IF($S28="", "", ROUND($S28 - $K28,2))) | U28: =IF($A28="","",IF($K28="", "", ROUND((($K28 + Settings!$B$3 + $R28) - IF($M28="",0,$M28))/(1-Settings!$B$2),2))) | V28: =IF($A28="","",$L28-($L28*Settings!$B$2)-$J28-($B28+SUM($D28:$I28))) | W28: =IF($A28="","",(($B28+SUM($D28:$I28)+$J28+Settings!$B$3)/(1-Settings!$B$2))-$M28) | X28: =IF($A28="","",IF($O28="", "", IFERROR($T28/$O28, ""))) | Y28: =IF($A28="","",IF($K28="", "", IFERROR($T28/$K28, ""))) | Z28: =IF($A28="","",IF($O28="", "", IFERROR($Q28/$O28, ""))) | AA28: =IF($A28="","",IF($L28="", "", IFERROR($T28/$L28, ""))) | AE28: =IF($A28="","",IF(OR($AC28="", $AD28=""),"", $AD28-$AC28))
C29: ESE (Ding Defend) | D29: =IF($A29="","",1*'Material Costs'!$D$3) | E29: =IF($A29="","",1*'Material Costs'!$D$2) | F29: =IF($A29="","",IF($C29="Bubble Mailer",2,1)*'Material Costs'!$D$6) | G29: =IF($A29="","",1*'Material Costs'!$D$7) | H29: =IF($A29="","",IF($C29="Bubble Mailer",1,0)*'Material Costs'!$D$5) | I29: =IF($A29="","",IF($C29="ESE (Ding Defend)",1,0)*'Material Costs'!$D$4) | K29: =IF($A29="","",SUM($B29:$J29)) | O29: =IF($A29="","",SUM($L29:$N29)) | Q29: =IF($A29="","",IF($O29="", "", ROUND($O29*Settings!$B$2+Settings!$B$3,2))) | R29: =IF($A29="","",IF($L29="", "", Settings!$B$4)) | S29: =IF($A29="","",IF($O29="", "", ROUND($O29 - IF($P29<>"",$P29,$Q29) - $R29,2))) | T29: =IF($A29="","",IF($S29="", "", ROUND($S29 - $K29,2))) | U29: =IF($A29="","",IF($K29="", "", ROUND((($K29 + Settings!$B$3 + $R29) - IF($M29="",0,$M29))/(1-Settings!$B$2),2))) | V29: =IF($A29="","",$L29-($L29*Settings!$B$2)-$J29-($B29+SUM($D29:$I29))) | W29: =IF($A29="","",(($B29+SUM($D29:$I29)+$J29+Settings!$B$3)/(1-Settings!$B$2))-$M29) | X29: =IF($A29="","",IF($O29="", "", IFERROR($T29/$O29, ""))) | Y29: =IF($A29="","",IF($K29="", "", IFERROR($T29/$K29, ""))) | Z29: =IF($A29="","",IF($O29="", "", IFERROR($Q29/$O29, ""))) | AA29: =IF($A29="","",IF($L29="", "", IFERROR($T29/$L29, ""))) | AE29: =IF($A29="","",IF(OR($AC29="", $AD29=""),"", $AD29-$AC29))
C30: ESE (Ding Defend) | D30: =IF($A30="","",1*'Material Costs'!$D$3) | E30: =IF($A30="","",1*'Material Costs'!$D$2) | F30: =IF($A30="","",IF($C30="Bubble Mailer",2,1)*'Material Costs'!$D$6) | G30: =IF($A30="","",1*'Material Costs'!$D$7) | H30: =IF($A30="","",IF($C30="Bubble Mailer",1,0)*'Material Costs'!$D$5) | I30: =IF($A30="","",IF($C30="ESE (Ding Defend)",1,0)*'Material Costs'!$D$4) | K30: =IF($A30="","",SUM($B30:$J30)) | O30: =IF($A30="","",SUM($L30:$N30)) | Q30: =IF($A30="","",IF($O30="", "", ROUND($O30*Settings!$B$2+Settings!$B$3,2))) | R30: =IF($A30="","",IF($L30="", "", Settings!$B$4)) | S30: =IF($A30="","",IF($O30="", "", ROUND($O30 - IF($P30<>"",$P30,$Q30) - $R30,2))) | T30: =IF($A30="","",IF($S30="", "", ROUND($S30 - $K30,2))) | U30: =IF($A30="","",IF($K30="", "", ROUND((($K30 + Settings!$B$3 + $R30) - IF($M30="",0,$M30))/(1-Settings!$B$2),2))) | V30: =IF($A30="","",$L30-($L30*Settings!$B$2)-$J30-($B30+SUM($D30:$I30))) | W30: =IF($A30="","",(($B30+SUM($D30:$I30)+$J30+Settings!$B$3)/(1-Settings!$B$2))-$M30) | X30: =IF($A30="","",IF($O30="", "", IFERROR($T30/$O30, ""))) | Y30: =IF($A30="","",IF($K30="", "", IFERROR($T30/$K30, ""))) | Z30: =IF($A30="","",IF($O30="", "", IFERROR($Q30/$O30, ""))) | AA30: =IF($A30="","",IF($L30="", "", IFERROR($T30/$L30, ""))) | AE30: =IF($A30="","",IF(OR($AC30="", $AD30=""),"", $AD30-$AC30))
C31: ESE (Ding Defend) | D31: =IF($A31="","",1*'Material Costs'!$D$3) | E31: =IF($A31="","",1*'Material Costs'!$D$2) | F31: =IF($A31="","",IF($C31="Bubble Mailer",2,1)*'Material Costs'!$D$6) | G31: =IF($A31="","",1*'Material Costs'!$D$7) | H31: =IF($A31="","",IF($C31="Bubble Mailer",1,0)*'Material Costs'!$D$5) | I31: =IF($A31="","",IF($C31="ESE (Ding Defend)",1,0)*'Material Costs'!$D$4) | K31: =IF($A31="","",SUM($B31:$J31)) | O31: =IF($A31="","",SUM($L31:$N31)) | Q31: =IF($A31="","",IF($O31="", "", ROUND($O31*Settings!$B$2+Settings!$B$3,2))) | R31: =IF($A31="","",IF($L31="", "", Settings!$B$4)) | S31: =IF($A31="","",IF($O31="", "", ROUND($O31 - IF($P31<>"",$P31,$Q31) - $R31,2))) | T31: =IF($A31="","",IF($S31="", "", ROUND($S31 - $K31,2))) | U31: =IF($A31="","",IF($K31="", "", ROUND((($K31 + Settings!$B$3 + $R31) - IF($M31="",0,$M31))/(1-Settings!$B$2),2))) | V31: =IF($A31="","",$L31-($L31*Settings!$B$2)-$J31-($B31+SUM($D31:$I31))) | W31: =IF($A31="","",(($B31+SUM($D31:$I31)+$J31+Settings!$B$3)/(1-Settings!$B$2))-$M31) | X31: =IF($A31="","",IF($O31="", "", IFERROR($T31/$O31, ""))) | Y31: =IF($A31="","",IF($K31="", "", IFERROR($T31/$K31, ""))) | Z31: =IF($A31="","",IF($O31="", "", IFERROR($Q31/$O31, ""))) | AA31: =IF($A31="","",IF($L31="", "", IFERROR($T31/$L31, ""))) | AE31: =IF($A31="","",IF(OR($AC31="", $AD31=""),"", $AD31-$AC31))
C32: ESE (Ding Defend) | D32: =IF($A32="","",1*'Material Costs'!$D$3) | E32: =IF($A32="","",1*'Material Costs'!$D$2) | F32: =IF($A32="","",IF($C32="Bubble Mailer",2,1)*'Material Costs'!$D$6) | G32: =IF($A32="","",1*'Material Costs'!$D$7) | H32: =IF($A32="","",IF($C32="Bubble Mailer",1,0)*'Material Costs'!$D$5) | I32: =IF($A32="","",IF($C32="ESE (Ding Defend)",1,0)*'Material Costs'!$D$4) | K32: =IF($A32="","",SUM($B32:$J32)) | O32: =IF($A32="","",SUM($L32:$N32)) | Q32: =IF($A32="","",IF($O32="", "", ROUND($O32*Settings!$B$2+Settings!$B$3,2))) | R32: =IF($A32="","",IF($L32="", "", Settings!$B$4)) | S32: =IF($A32="","",IF($O32="", "", ROUND($O32 - IF($P32<>"",$P32,$Q32) - $R32,2))) | T32: =IF($A32="","",IF($S32="", "", ROUND($S32 - $K32,2))) | U32: =IF($A32="","",IF($K32="", "", ROUND((($K32 + Settings!$B$3 + $R32) - IF($M32="",0,$M32))/(1-Settings!$B$2),2))) | V32: =IF($A32="","",$L32-($L32*Settings!$B$2)-$J32-($B32+SUM($D32:$I32))) | W32: =IF($A32="","",(($B32+SUM($D32:$I32)+$J32+Settings!$B$3)/(1-Settings!$B$2))-$M32) | X32: =IF($A32="","",IF($O32="", "", IFERROR($T32/$O32, ""))) | Y32: =IF($A32="","",IF($K32="", "", IFERROR($T32/$K32, ""))) | Z32: =IF($A32="","",IF($O32="", "", IFERROR($Q32/$O32, ""))) | AA32: =IF($A32="","",IF($L32="", "", IFERROR($T32/$L32, ""))) | AE32: =IF($A32="","",IF(OR($AC32="", $AD32=""),"", $AD32-$AC32))
C33: ESE (Ding Defend) | D33: =IF($A33="","",1*'Material Costs'!$D$3) | E33: =IF($A33="","",1*'Material Costs'!$D$2) | F33: =IF($A33="","",IF($C33="Bubble Mailer",2,1)*'Material Costs'!$D$6) | G33: =IF($A33="","",1*'Material Costs'!$D$7) | H33: =IF($A33="","",IF($C33="Bubble Mailer",1,0)*'Material Costs'!$D$5) | I33: =IF($A33="","",IF($C33="ESE (Ding Defend)",1,0)*'Material Costs'!$D$4) | K33: =IF($A33="","",SUM($B33:$J33)) | O33: =IF($A33="","",SUM($L33:$N33)) | Q33: =IF($A33="","",IF($O33="", "", ROUND($O33*Settings!$B$2+Settings!$B$3,2))) | R33: =IF($A33="","",IF($L33="", "", Settings!$B$4)) | S33: =IF($A33="","",IF($O33="", "", ROUND($O33 - IF($P33<>"",$P33,$Q33) - $R33,2))) | T33: =IF($A33="","",IF($S33="", "", ROUND($S33 - $K33,2))) | U33: =IF($A33="","",IF($K33="", "", ROUND((($K33 + Settings!$B$3 + $R33) - IF($M33="",0,$M33))/(1-Settings!$B$2),2))) | V33: =IF($A33="","",$L33-($L33*Settings!$B$2)-$J33-($B33+SUM($D33:$I33))) | W33: =IF($A33="","",(($B33+SUM($D33:$I33)+$J33+Settings!$B$3)/(1-Settings!$B$2))-$M33) | X33: =IF($A33="","",IF($O33="", "", IFERROR($T33/$O33, ""))) | Y33: =IF($A33="","",IF($K33="", "", IFERROR($T33/$K33, ""))) | Z33: =IF($A33="","",IF($O33="", "", IFERROR($Q33/$O33, ""))) | AA33: =IF($A33="","",IF($L33="", "", IFERROR($T33/$L33, ""))) | AE33: =IF($A33="","",IF(OR($AC33="", $AD33=""),"", $AD33-$AC33))
C34: ESE (Ding Defend) | D34: =IF($A34="","",1*'Material Costs'!$D$3) | E34: =IF($A34="","",1*'Material Costs'!$D$2) | F34: =IF($A34="","",IF($C34="Bubble Mailer",2,1)*'Material Costs'!$D$6) | G34: =IF($A34="","",1*'Material Costs'!$D$7) | H34: =IF($A34="","",IF($C34="Bubble Mailer",1,0)*'Material Costs'!$D$5) | I34: =IF($A34="","",IF($C34="ESE (Ding Defend)",1,0)*'Material Costs'!$D$4) | K34: =IF($A34="","",SUM($B34:$J34)) | O34: =IF($A34="","",SUM($L34:$N34)) | Q34: =IF($A34="","",IF($O34="", "", ROUND($O34*Settings!$B$2+Settings!$B$3,2))) | R34: =IF($A34="","",IF($L34="", "", Settings!$B$4)) | S34: =IF($A34="","",IF($O34="", "", ROUND($O34 - IF($P34<>"",$P34,$Q34) - $R34,2))) | T34: =IF($A34="","",IF($S34="", "", ROUND($S34 - $K34,2))) | U34: =IF($A34="","",IF($K34="", "", ROUND((($K34 + Settings!$B$3 + $R34) - IF($M34="",0,$M34))/(1-Settings!$B$2),2))) | V34: =IF($A34="","",$L34-($L34*Settings!$B$2)-$J34-($B34+SUM($D34:$I34))) | W34: =IF($A34="","",(($B34+SUM($D34:$I34)+$J34+Settings!$B$3)/(1-Settings!$B$2))-$M34) | X34: =IF($A34="","",IF($O34="", "", IFERROR($T34/$O34, ""))) | Y34: =IF($A34="","",IF($K34="", "", IFERROR($T34/$K34, ""))) | Z34: =IF($A34="","",IF($O34="", "", IFERROR($Q34/$O34, ""))) | AA34: =IF($A34="","",IF($L34="", "", IFERROR($T34/$L34, ""))) | AE34: =IF($A34="","",IF(OR($AC34="", $AD34=""),"", $AD34-$AC34))
C35: ESE (Ding Defend) | D35: =IF($A35="","",1*'Material Costs'!$D$3) | E35: =IF($A35="","",1*'Material Costs'!$D$2) | F35: =IF($A35="","",IF($C35="Bubble Mailer",2,1)*'Material Costs'!$D$6) | G35: =IF($A35="","",1*'Material Costs'!$D$7) | H35: =IF($A35="","",IF($C35="Bubble Mailer",1,0)*'Material Costs'!$D$5) | I35: =IF($A35="","",IF($C35="ESE (Ding Defend)",1,0)*'Material Costs'!$D$4) | K35: =IF($A35="","",SUM($B35:$J35)) | O35: =IF($A35="","",SUM($L35:$N35)) | Q35: =IF($A35="","",IF($O35="", "", ROUND($O35*Settings!$B$2+Settings!$B$3,2))) | R35: =IF($A35="","",IF($L35="", "", Settings!$B$4)) | S35: =IF($A35="","",IF($O35="", "", ROUND($O35 - IF($P35<>"",$P35,$Q35) - $R35,2))) | T35: =IF($A35="","",IF($S35="", "", ROUND($S35 - $K35,2))) | U35: =IF($A35="","",IF($K35="", "", ROUND((($K35 + Settings!$B$3 + $R35) - IF($M35="",0,$M35))/(1-Settings!$B$2),2))) | V35: =IF($A35="","",$L35-($L35*Settings!$B$2)-$J35-($B35+SUM($D35:$I35))) | W35: =IF($A35="","",(($B35+SUM($D35:$I35)+$J35+Settings!$B$3)/(1-Settings!$B$2))-$M35) | X35: =IF($A35="","",IF($O35="", "", IFERROR($T35/$O35, ""))) | Y35: =IF($A35="","",IF($K35="", "", IFERROR($T35/$K35, ""))) | Z35: =IF($A35="","",IF($O35="", "", IFERROR($Q35/$O35, ""))) | AA35: =IF($A35="","",IF($L35="", "", IFERROR($T35/$L35, ""))) | AE35: =IF($A35="","",IF(OR($AC35="", $AD35=""),"", $AD35-$AC35))
... C501: ESE (Ding Defend) | D501: =IF($A501="","",1*'Material Costs'!$D$3) | E501: =IF($A501="","",1*'Material Costs'!$D$2) | F501: =IF($A501="","",IF($C501="Bubble Mailer",2,1)*'Material Costs'!$D$6) | G501: =IF($A501="","",1*'Material Costs'!$D$7) | H501: =IF($A501="","",IF($C501="Bubble Mailer",1,0)*'Material Costs'!$D$5) | I501: =IF($A501="","",IF($C501="ESE (Ding Defend)",1,0)*'Material Costs'!$D$4) | K501: =IF($A501="","",SUM($B501:$J501)) | O501: =IF($A501="","",SUM($L501:$N501)) | Q501: =IF($A501="","",IF($O501="", "", ROUND($O501*Settings!$B$2+Settings!$B$3,2))) | R501: =IF($A501="","",IF($L501="", "", Settings!$B$4)) | S501: =IF($A501="","",IF($O501="", "", ROUND($O501 - IF($P501<>"",$P501,$Q501) - $R501,2))) | T501: =IF($A501="","",IF($S501="", "", ROUND($S501 - $K501,2))) | U501: =IF($A501="","",IF($K501="", "", ROUND((($K501 + Settings!$B$3 + $R501) - IF($M501="",0,$M501))/(1-Settings!$B$2),2))) | V501: =IF($A501="","",$L501-($L501*Settings!$B$2)-$J501-($B501+SUM($D501:$I501))) | W501: =IF($A501="","",(($B501+SUM($D501:$I501)+$J501+Settings!$B$3)/(1-Settings!$B$2))-$M501) | X501: =IF($A501="","",IF($O501="", "", IFERROR($T501/$O501, ""))) | Y501: =IF($A501="","",IF($K501="", "", IFERROR($T501/$K501, ""))) | Z501: =IF($A501="","",IF($O501="", "", IFERROR($Q501/$O501, ""))) | AA501: =IF($A501="","",IF($L501="", "", IFERROR($T501/$L501, ""))) | AE501: =IF($A501="","",IF(OR($AC501="", $AD501=""),"", $AD501-$AC501))
A502: Notes: | B502: Enter Sales Tax + eBay Transaction Fees (Actual) from the order details when possible. If the Actual fee is blank, the sheet uses the Estimate (Settings tab). Order Earnings exclude sales tax (since eBay collects it). | D502: =IF($A502="","",1*'Material Costs'!$D$3) -> 0.01716 | E502: =IF($A502="","",1*'Material Costs'!$D$2) -> 0.1699 | F502: =IF($A502="","",IF($C502="Bubble Mailer",2,1)*'Material Costs'!$D$6) -> 0.1712 | G502: =IF($A502="","",1*'Material Costs'!$D$7) -> 0.0525 | H502: =IF($A502="","",IF($C502="Bubble Mailer",1,0)*'Material Costs'!$D$5) -> 0 | I502: =IF($A502="","",IF($C502="ESE (Ding Defend)",1,0)*'Material Costs'!$D$4) -> 0 | K502: =IF($A502="","",SUM($B502:$J502)) -> 0.41076 | O502: =IF($A502="","",SUM($L502:$N502)) -> 0 | Q502: =IF($A502="","",IF($O502="", "", ROUND($O502*Settings!$B$2+Settings!$B$3,2))) -> 0.3 | R502: =IF($A502="","",IF($L502="", "", Settings!$B$4)) | S502: =IF($A502="","",IF($O502="", "", ROUND($O502 - IF($P502<>"",$P502,$Q502) - $R502,2))) -> #VALUE! | T502: =IF($A502="","",IF($S502="", "", ROUND($S502 - $K502,2))) -> #VALUE! | U502: =IF($A502="","",IF($K502="", "", ROUND((($K502 + Settings!$B$3 + $R502) - IF($M502="",0,$M502))/(1-Settings!$B$2),2))) -> #VALUE! | X502: =IF($A502="","",IF($O502="", "", IFERROR($T502/$O502, ""))) | Y502: =IF($A502="","",IF($K502="", "", IFERROR($T502/$K502, ""))) | Z502: =IF($A502="","",IF($O502="", "", IFERROR($Q502/$O502, ""))) | AA502: =IF($A502="","",IF($L502="", "", IFERROR($T502/$L502, ""))) | AE502: =IF($A502="","",IF(OR($AC502="", $AD502=""),"", $AD502-$AC502))

Sheet Material Costs
A1: Material | B1: Pack Count | C1: Pack Price | D1: Cost Per Unit (Calc) | E1: Cost Per Unit (Rounded)
A2: Ultra Pro 3x4 Top Loaders | B2: 200 | C2: 33.98 | D2: 0.1699 | E2: 0.17
A3: Ultra Pro Penny Sleeves | B3: 500 | C3: 8.58 | D3: 0.01716 | E3: 0.02
A4: Ding Defend Card Shipping Envelopes | B4: 110 | C4: 24.97 | D4: 0.227 | E4: 0.23
A5: Bubble Mailers 4x7 Poly Padded (packbabol) | B5: 50 | C5: 9.88 | D5: 0.1976 | E5: 0.2
A6: Hobby Armor 3.5x4.5 Rounded Corners | B6: 50 | C6: 8.56 | D6: 0.1712 | E6: 0.17
A7: Team Bags 3x4 (35pt) - DEDC | B7: 100 | C7: 5.25 | D7: 0.0525 | E7: 0.05
A8: Graded Card Sleeves Resealable (Lewtemi) | B8: 300 | C8: 7.99 | D8: 0.026633333 | E8: 0.03
A10: Note: Penny sleeves are $8.58/500 = $0.0172 each (not $0.01). Cost/Unit here is calculated as Pack Price ÷ Pack Count.

Sheet Settings
A1: Setting | B1: Value | C1: Notes
A2: eBay fee rate (estimate) | B2: 0.1325 | C2: Used when actual fee isn’t entered. Edit to match your category/rate.
A3: eBay fixed fee per order (estimate) | B3: 0.3 | C3: Fixed component used in estimate.
A4: Insertion fee after free allotment | B4: 0.25 | C4: Basic Store: 1,000 fixed-price listings/month included; after that ~$0.25 each (per your screenshot).
